LICENSE
MANIFEST.in
README.rst
amalgamate.py
setup.py
amalgamate.egg-info/PKG-INFO
amalgamate.egg-info/SOURCES.txt
amalgamate.egg-info/dependency_links.txt
amalgamate.egg-info/not-zip-safe
amalgamate.egg-info/top_level.txt