Metadata-Version: 1.1
Name: amalgamate
Version: 0.1.2
Summary: Collapses Python packages into a single module.
Home-page: https://github.com/xonsh/amalgamate
Author: The xonsh developers
Author-email: xonsh@googlegroups.com
License: BSD 3-clause
Download-URL: https://github.com/xonsh/amalgamate/zipball/0.1.2
Platform: UNKNOWN
Classifier: License :: OSI Approved
Classifier: Intended Audience :: Developers
Classifier: Programming Language :: Python
Classifier: Topic :: Utilities
